wavescout/__init__.py
wavescout/main.py
wavescout/wavescout.py
wavescout-0.1.0.dist-info/METADATA
wavescout-0.1.0.dist-info/WHEEL
wavescout-0.1.0.dist-info/entry_points.txt
wavescout-0.1.0.dist-info/RECORD
