Metadata-Version: 2.1
Name: wavescout
Version: 0.1.0
Summary: A lightweight module for easy beatmapping, key detection, and smart-slicing
License: MIT
Author: DJ Stomp
Author-email: 85457381+DJStompZone@users.noreply.github.com
Requires-Python: >=3.10,<4.0
Classifier: License :: OSI Approved :: MIT License
Classifier: Programming Language :: Python :: 3
Classifier: Programming Language :: Python :: 3.10
Classifier: Programming Language :: Python :: 3.11
Requires-Dist: aubio (>=0.4.9,<0.5.0)
Requires-Dist: build (>=0.10.0,<0.11.0)
Requires-Dist: click (>=8.1.3,<9.0.0)
Requires-Dist: essentia (==2.1b6.dev858)
Requires-Dist: pydub (>=0.25.1,<0.26.0)
Requires-Dist: pytest (>=7.3.1,<8.0.0)
Requires-Dist: twine (>=4.0.2,<5.0.0)
